makemypip/__init__.py
makemypip/__main__.py
makemypip/makemypip.py
makemypip-0.2.dist-info/LICENCE
makemypip-0.2.dist-info/METADATA
makemypip-0.2.dist-info/WHEEL
makemypip-0.2.dist-info/entry_points.txt
makemypip-0.2.dist-info/top_level.txt
makemypip-0.2.dist-info/RECORD
