Metadata-Version: 2.1
Name: makemypip
Version: 0.2
Summary: python pip packager
Home-page: UNKNOWN
Author: Spr3z
Author-email: zezo.665.5@gmail.com
License: UNKNOWN
Platform: UNKNOWN
Classifier: Programming Language :: Python :: 3
Classifier: License :: OSI Approved :: MIT License
Classifier: Operating System :: OS Independent
